cubicweb_task/__init__.py
cubicweb_task/__pkginfo__.py
cubicweb_task/entities.py
cubicweb_task/hooks.py
cubicweb_task/schema.py
cubicweb_task/views.py
cubicweb_task/data/icon_task.gif
cubicweb_task/i18n/en.po
cubicweb_task/i18n/fr.po
cubicweb_task/migration/1.6.0_Any.py
cubicweb_task/migration/1.6.1_Any.py
cubicweb_task/migration/1.8.1_Any.py
cubicweb_task/migration/postcreate.py
cubicweb_task-2.1.0.dist-info/METADATA
cubicweb_task-2.1.0.dist-info/WHEEL
cubicweb_task-2.1.0.dist-info/entry_points.txt
cubicweb_task-2.1.0.dist-info/top_level.txt
cubicweb_task-2.1.0.dist-info/RECORD
